QNBHelper/QNBFaturaCreator.py
QNBHelper/__init__.py
QNBHelper/models/Accounting.py
QNBHelper/models/Address.py
QNBHelper/models/Contact.py
QNBHelper/models/Input.py
QNBHelper/models/Invoice.py
QNBHelper/models/InvoiceLine.py
QNBHelper/models/LegalMonetaryTotal.py
QNBHelper/models/Note.py
QNBHelper/models/Request.py
QNBHelper/models/Response.py
QNBHelper/models/Tax.py
QNBHelper/models/__init__.py
QNBHelper/utils/__init__.py
QNBHelper/utils/utils.py
qnb_invoice_helper-1.1.2.dist-info/METADATA
qnb_invoice_helper-1.1.2.dist-info/WHEEL
qnb_invoice_helper-1.1.2.dist-info/top_level.txt
qnb_invoice_helper-1.1.2.dist-info/RECORD
