Metadata-Version: 2.2
Name: qnb-invoice-helper
Version: 1.1.2
Summary: QNB Invoice Creator
Author: Esat Yılmaz
Author-email: esatyilmaz3500@gmail.com
Classifier: Programming Language :: Python :: 3.9
Classifier: License :: OSI Approved :: MIT License
Classifier: Operating System :: OS Independent
Requires-Python: >=3.9
Requires-Dist: pydantic
Requires-Dist: requests
Requires-Dist: zeep
Dynamic: author
Dynamic: author-email
Dynamic: classifier
Dynamic: requires-dist
Dynamic: requires-python
Dynamic: summary
